{"Trip":[{"LegList":{"Leg":[{"Origin":{"type":"ST","time":"15:12:00","date":"2022-01-09","name":"Abbekås (Skurup kn)","id":"740001006","extId":"740001006","routeIdx":26,"lon":13.593695,"lat":55.394083},"Destination":{"time":"15:15:00","date":"2022-01-09","name":"Abbekås Ö (Skurup kn)","id":"740013938","extId":"740013938","routeIdx":27,"lon":13.610073,"lat":55.405508},"Product":{"name":"Länstrafik - Buss 190","num":"190","catCode":"7","catOutS":"BLT","catOutL":"Länstrafik - Buss","operatorCode":"276","operator":"Skånetrafiken","operatorUrl":"http://www.skanetrafiken.se"},"Stops":{"Stop":[{"name":"Abbekås (Skurup kn)","id":"740001006","extId":"740001006","routeIdx":26,"lon":13.593695,"lat":55.394083,"depTime":"15:12:00","depDate":"2022-01-09"},{"name":"Abbekås Ö (Skurup kn)","id":"740013938","extId":"740013938","routeIdx":27,"lon":13.610073,"lat":55.405508,"arrTime":"15:15:00","arrDate":"2022-01-09"}]},"idx":"0","name":"Länstrafik - Buss 190","transportNumber":"190","transportCategory":"BLT","type":"JNY","reachable":true,"direction":"Ystad station"}]},"idx":0,"tripId":"C-0","ctxRecon":"T$A\u003d1@O\u003dAbbekås (Skurup kn)@L\u003d740001006@a\u003d128@$A\u003d1@O\u003dAbbekås Ö (Skurup kn)@L\u003d740013938@a\u003d128@$202201091512$202201091515$BLT  190$$1$","duration":"PT3M"}],"scrB":"1|OB|MTµ11µ10992µ10992µ10995µ10995µ0µ0µ365µ10978µ1µ-2147482382µ0µ1µ2|PDHµcf37ff9b53467dbeb158af8033959697|RDµ9012022|RTµ145832","scrF":"1|OF|MTµ11µ10992µ10992µ10995µ10995µ0µ0µ365µ10978µ1µ-2147482382µ0µ1µ2|PDHµcf37ff9b53467dbeb158af8033959697|RDµ9012022|RTµ145832"}